lookml/__init__.py
lookml/__main__.py
lookml/cli/__init__.py
lookml/cli/autotune/__init__.py
lookml/cli/autotune/autotune.py
lookml/cli/directory/__init__.py
lookml/cli/directory/directory.py
lookml/cli/doctree/__init__.py
lookml/cli/doctree/doctree.py
lookml/core.py
lookml/lib/__init__.py
lookml/lib/lang.py
lookml/lib/language_data/__init__.py
lookml/lib/language_data/_allowed_children.py
lookml/lib/language_data/config.py
lookml/lib/project.py
lookml/lib/utils.py
lookml/lkml/__init__.py
lookml/lkml/keys.py
lookml/lkml/lexer.py
lookml/lkml/parser.py
lookml/lkml/serializer.py
lookml/lkml/tokens.py
lookml/tests/__init__.py
lookml/tests/files/basic_parsing/agg.model.lkml
lookml/tests/files/basic_parsing/basic.model.lkml
lookml/tests/files/basic_parsing/basic.view.lkml
lookml/tests/files/basic_parsing/manifest.lkml
lookml/tests/files/basic_parsing/refine.view.lkml
lookml/tests/files/kitchenSink/kitchenSink.model.lkml
lookml/tests/files/kitchenSink/kitchenSink2.model.lkml
lookml/tests/files/order_items.view.lkml
lookml/tests/files/pylookml_test_project/dashboards/.gitkeep
lookml/tests/files/pylookml_test_project/dashboards/brand_lookup.dashboard.lookml
lookml/tests/files/pylookml_test_project/dashboards/business_pulse.dashboard.lookml
lookml/tests/files/pylookml_test_project/dashboards/customer_lookup.dashboard.lookml
lookml/tests/files/pylookml_test_project/dashboards/shipping_logistics_overview.dashboard.lookml
lookml/tests/files/pylookml_test_project/dashboards/web_analytics_overview.dashboard.lookml
lookml/tests/files/pylookml_test_project/manifest.lkml
lookml/tests/files/pylookml_test_project/models/.gitkeep
lookml/tests/files/pylookml_test_project/models/pylookml_testing.model.lkml
lookml/tests/files/pylookml_test_project/models/queries_for_order_items.view.lkml
lookml/tests/files/pylookml_test_project/scratch/subfolder/pylookml_scratch.view.lkml
lookml/tests/files/pylookml_test_project/views/.gitkeep
lookml-3.0.3.dist-info/entry_points.txt
lookml-3.0.3.dist-info/LICENSE
lookml-3.0.3.dist-info/WHEEL
lookml-3.0.3.dist-info/METADATA
lookml-3.0.3.dist-info/RECORD
